paperviz/__init__.py
paperviz/area/__init__.py
paperviz/area/area.py
paperviz/bar/__init__.py
paperviz/bar/bar.py
paperviz/box/__init__.py
paperviz/box/box.py
paperviz/heatmap/__init__.py
paperviz/heatmap/heatmap.py
paperviz/histogram/__init__.py
paperviz/histogram/histogram.py
paperviz/line/__init__.py
paperviz/line/line.py
paperviz/pie/__init__.py
paperviz/pie/pie.py
paperviz/pyramid/__init__.py
paperviz/pyramid/pyramid.py
paperviz/time_series/__init__.py
paperviz/time_series/time_series.py
paperviz/violin/__init__.py
paperviz/violin/violin.py
Paper_Viz-1.0.2.dist-info/LICENSE
Paper_Viz-1.0.2.dist-info/METADATA
Paper_Viz-1.0.2.dist-info/WHEEL
Paper_Viz-1.0.2.dist-info/top_level.txt
Paper_Viz-1.0.2.dist-info/RECORD
