Metadata-Version: 2.1
Name: Paper-Viz
Version: 1.0.2
Summary: Professional Python Graphs for Scientific Papers
Home-page: https://github.com/swsamleo/Paper-Viz
Author: CRUISE Group
Author-email: wei.shao@rmit.edu.au
License: GNU GPLv3
Keywords: scientific papers,professional python graphs,thesis template,python
Platform: UNKNOWN
Classifier: Programming Language :: Python :: 3
License-File: LICENSE
Requires-Dist: numpy
Requires-Dist: pandas
Requires-Dist: matplotlib
Requires-Dist: seaborn
